Workbook

Sheet LM AIOE
A1: SOC Code | B1: Occupation Title | C1: Language Modeling AIOE
A2: 11-1011 | B2: Chief Executives | C2: 1.308912 | E2: =COUNT(C2:C775) -> 774
A3: 11-1021 | B3: General and Operations Managers | C3: 0.6776147 | E3: =COUNTA(C2:C775) -> 774
A4: 11-2011 | B4: Advertising and Promotions Managers | C4: 1.217224 | F4: Check the SOC codes | G4: {=SUMPRODUCT(--(LEN('LM AIOE'!A2:A775)<>7))} -> 0
A5: 11-2021 | B5: Marketing Managers | C5: 1.203774 | D5: Minimum score | E5: =MIN(C2:C775) -> -1.853906 | F5: Validate the SOC code format | G5: {=SUMPRODUCT(--(MID(A2:A775,3,1)<>"-"))} -> 0
A6: 11-2022 | B6: Sales Managers | C6: 1.293821 | D6: Maximum score | E6: =MAX(C2:C775) -> 1.925633
A7: 11-2031 | B7: Public Relations and Fundraising Managers | C7: 1.382948 | D7: Average score | E7: =AVERAGE(C2:C775) -> 3.8759691e-09
A8: 11-3011 | B8: Administrative Services Managers | C8: 0.7681937 | D8: Negative scores | E8: =COUNTIF(C2:C775,"<0") -> 409
A9: 11-3021 | B9: Computer and Information Systems Managers | C9: 0.9450699 | D9: Zero scores | E9: =COUNTIF(C2:C775,0) -> 0
A10: 11-3031 | B10: Financial Managers | C10: 1.294551
A11: 11-3051 | B11: Industrial Production Managers | C11: 0.3542972
A12: 11-3061 | B12: Purchasing Managers | C12: 1.393102
A13: 11-3071 | B13: Transportation, Storage, and Distribution Managers | C13: 0.9045479
A14: 11-3111 | B14: Compensation and Benefits Managers | C14: 1.466744
A15: 11-3121 | B15: Human Resources Managers | C15: 1.359222
A16: 11-3131 | B16: Training and Development Managers | C16: 1.336838
A17: 11-9013 | B17: Farmers, Ranchers, and Other Agricultural Managers | C17: -0.1584996
A18: 11-9021 | B18: Construction Managers | C18: 0.6361951
A19: 11-9031 | B19: Education Administrators, Preschool and Childcare Center/Program | C19: 0.9671877
A20: 11-9032 | B20: Education Administrators, Elementary and Secondary School | C20: 1.199449
A21: 11-9033 | B21: Education Administrators, Postsecondary | C21: 1.544923
... A775: 53-7121 | B775: Tank Car, Truck, and Ship Loaders | C775: -1.403185

Sheet LM AIIE
A1: NAICS | B1: NAICS Description | C1: Language Modeling AIIE
A2: 611100 | B2: Elementary and Secondary Schools | C2: 1.44894 | F2: COUNTA | G2: =COUNTA(A2:A251) -> 250
A3: 551100 | B3: Management of Companies and Enterprises | C3: 1.592071 | F3: COUNT | G3: =COUNT(A2:A251) -> 0
A4: 445300 | B4: Beer, Wine, and Liquor Stores | C4: 0.2288 | E4: =COUNT(C2:C251) -> 250 | F4: Check the NAICS code format | G4: {=SUMPRODUCT(--(LEN(A2:A251)<>6))} -> 0
A5: 444100 | B5: Building Material and Supplies Dealers | C5: 0.3544964 | E5: =COUNTA(C2:C251) -> 250
A6: 312200 | B6: Tobacco Manufacturing | C6: -0.9705914
A7: 221200 | B7: Natural Gas Distribution | C7: 0.2033846 | D7: Minimum score | E7: =MIN(C2:C251) -> -1.93639
A8: 334200 | B8: Communications Equipment Manufacturing | C8: 0.991125 | D8: Maximum score | E8: =MAX(C2:C251) -> 2.19893
A9: 451100 | B9: Sporting Goods, Hobby, and Musical Instrument Stores | C9: 0.513244 | D9: Average score | E9: =AVERAGE(C2:C251) -> 1.2e-09
A10: 621900 | B10: Other Ambulatory Health Care Services | C10: 0.7634743 | D10: Negative scores | E10: =COUNTIF(C2:C251,"<0") -> 138
A11: 811200 | B11: Electronic and Precision Equipment Repair and Maintenance | C11: -0.0773292 | D11: Zero scores | E11: =COUNTIF(C2:C251,0) -> 0
A12: 311900 | B12: Other Food Manufacturing | C12: -0.8497112
A13: 425100 | B13: Wholesale Electronic Markets and Agents and Brokers | C13: 1.062347
A14: 337900 | B14: Other Furniture Related Product Manufacturing | C14: -0.6635574
A15: 322200 | B15: Converted Paper Product Manufacturing | C15: -0.885119
A16: 611200 | B16: Junior Colleges | C16: 1.759217
A17: 3250A1 | B17: Chemical Manufacturing (3251, 3252, 3253, and 3259 only) | C17: -0.3177066
A18: 711200 | B18: Spectator Sports | C18: -0.0540171
A19: 334400 | B19: Semiconductor and Other Electronic Component Manufacturing | C19: 0.4500771
A20: 4240A2 | B20: Merchant Wholesalers, Nondurable Goods (4242 and 4246 only) | C20: 0.6972101
A21: 813100 | B21: Religious Organizations | C21: 1.155523
A22: 561900 | B22: Other Support Services | C22: -0.4006903
A23: 624400 | B23: Child Day Care Services | C23: 0.4045842
... A251: 448100 | B251: Clothing Stores | C251: 0.5698005

Sheet QC_Checks
A1: Column Checked | B1: Records With Extra Spaces
A2: SOC Code | B2: {=SUMPRODUCT(--(LEN('LM AIOE'!A2:A775)<>LEN(TRIM('LM AIOE'!A2:A775))))} -> 0
A3: Occupation Title | B3: {=SUMPRODUCT(--(LEN('LM AIOE'!B2:B775)<>LEN(TRIM('LM AIOE'!B2:B775))))} -> 0
A4: NAICS | B4: {=SUMPRODUCT(--(LEN('LM AIIE'!A2:A251)<>LEN(TRIM('LM AIIE'!A2:A251))))} -> 0
A5: NAICS Description | B5: {=SUMPRODUCT(--(LEN('LM AIIE'!B2:B251)<>LEN(TRIM('LM AIIE'!B2:B251))))} -> 0
